{
  "file_id": "etl-etl--s1",
  "status": "has_issues",
  "findings": [
    {
      "category": "hints_missing",
      "severity": "minor",
      "location": "index[s6].hints",
      "description": "s6のhintsに `sql_loader_merge` が含まれていない。ソースではSQL*Loaderマージモード用テンプレート（sql_loader_merge.xml、sql_loader_merge_config.json）が明示的に記載されており、他の類似テンプレート名（sql_loader_replace、chunk_replace、file_output）はhintsに含まれているが、sql_loader_mergeだけ漏れている。",
      "source_evidence": "ソースの「JOB定義ファイルとETL用JOB設定ファイルを作成する」セクションに「:download:`JOB定義ファイルのテンプレート <templates/sql_loader_merge.xml>`」「:download:`ETL用JOB設定ファイルテンプレート <templates/sql_loader_merge_config.json>`」が記載されている。"
    }
  ]
}