{
  "file_id": "releases-nablarch5u11-releasenote",
  "status": "has_issues",
  "findings": [
    {
      "category": "fabrication",
      "severity": "minor",
      "location": "s1 — No.17 JSR352 JobContext/StepContext一時領域の使用禁止",
      "description": "Knowledge file adds \"（transientUserData）\" as the API name for 一時領域, but this term does not appear anywhere in the source file. The source only says \"一時領域\" without naming the underlying JSR352 API field.",
      "source_evidence": "Source No.17: 「JobContext、StepContextの一時領域をアプリケーションでは使用してはならないことを注意点として追記しました。」— no mention of \"transientUserData\""
    },
    {
      "category": "omission",
      "severity": "minor",
      "location": "s1 — No.24 Example",
      "description": "No.24 (固定長データ入出力機能のExampleアプリケーション追加、nablarch-example-batch-ee 5u11) is entirely absent from the knowledge file. Users looking for example code for the fixed-length data feature would benefit from knowing this example exists.",
      "source_evidence": "Source No.24: 「本リリースにて、データバインドに固定長データの入出力機能が追加されたのに伴い、当該機能のExampleを追加しました。修正後のバージョン: nablarch-example-batch-ee 5u11」"
    },
    {
      "category": "hints_missing",
      "severity": "minor",
      "location": "s1 — hints array",
      "description": "Three identifiers present in the source are missing from hints: (1) `nablarch-example-batch-ee` — the module added in No.24; (2) `AttributeConverter` — the PascalCase class name central to the No.15 Dialect type-conversion change; (3) `nablarch-fw-standalone` — the module updated in No.9 (JSR352バッチ起動時properties指定).",
      "source_evidence": "No.24: \"nablarch-example-batch-ee 5u11\"; No.15: \"Dialectが使用する型変換処理(AttributeConverter)を差し替えたい場合\"; No.9: \"nablarch-fw-batch-ee 1.3.0 / nablarch-fw-standalone 1.2.0\""
    }
  ]
}