{
  "file_id": "web-application-12_keitai",
  "user_impact": "low",
  "needs_improvement": false,
  "reason": "The missing hints are feature names from the support status table. However, s1 already contains broad retrieval anchors (`携帯端末`, `フィーチャーフォン`) that cover the overwhelming majority of queries targeting this section. A developer asking about any of the missing features in a mobile context would likely phrase their query using these broad terms, ensuring s1 is retrieved. The section content itself is complete and accurate — all 12 features with correct support status and notes are present in the table. The missing hints reduce retrieval precision for highly specific single-term queries (e.g., `キャッシュ防止` alone, `入力画面・確認画面の共用化` alone) but do not cause practical retrieval failures for realistic usage patterns.",
  "findings_assessment": [
    {
      "category": "hints_missing",
      "location": "s1 hints",
      "impact": "low",
      "justification": "Seven feature names from the support status table are absent from s1 hints: `リクエストスコープ`, `送信URI動的切替`, `キャッシュ防止`, `ボタン・リンクによるフォーム送信`, `複数ウィンドウの制御`, `入力画面・確認画面の共用化`, `認可・開閉局判定に基づく表示制御`. However, (1) the broad hints `携帯端末` and `フィーチャーフォン` already anchor this section for any mobile-context query; (2) several missing features have partial coverage via related tag hints already present (`n:button`/`n:submitLink` cover ボタン・リンクによるフォーム送信; `n:popupLink` covers 複数ウィンドウの制御); (3) the section body contains the complete support table, so content quality is unaffected. The risk is limited to isolated single-term queries with no mobile context, which are atypical for this topic. Why it persisted: Phase E output is byte-for-byte identical to Phase D input — the fix was not applied at all. The improvement loop identified the issue but the E-phase agent failed to modify the hints array."
    }
  ]
}