{
  "file_id": "libraries-tag",
  "generated_at": "2026-03-04T03:47:50Z",
  "internal_labels": [],
  "sections": [
    {
      "section_id": "overview",
      "source_heading": "機能概要",
      "heading_level": "h2",
      "h3_split": false,
      "h3_split_reason": "Expected Sections list specifies only '機能概要' as single section; h3 subsections consolidated as nested headings within section. Pre-section intro content included as section preamble."
    },
    {
      "section_id": "modules",
      "source_heading": "モジュール一覧",
      "heading_level": "h2",
      "h3_split": false,
      "h3_split_reason": "plain text < 2000 chars, no h3 headings present"
    },
    {
      "section_id": "custom-tag-setting",
      "source_heading": "カスタムタグの設定",
      "heading_level": "h3",
      "h3_split": false,
      "h3_split_reason": "Expected Sections provided single item; source h3 with plain text < 2000 chars, no h3 split required"
    },
    {
      "section_id": "custom-tag-usage",
      "source_heading": "カスタムタグを使用する(taglibディレクティブの指定方法)",
      "heading_level": "h2",
      "h3_split": false,
      "h3_split_reason": "plain text ~35 chars < 2000 threshold, no h3 headings"
    },
    {
      "section_id": "input-form",
      "source_heading": "入力フォームを作る",
      "heading_level": "h2",
      "h3_split": false,
      "h3_split_reason": "plain text under 2000 characters"
    },
    {
      "section_id": "selection-items",
      "source_heading": "選択項目(プルダウン/ラジオボタン/チェックボックス)を表示する",
      "heading_level": "h2",
      "h3_split": false,
      "h3_split_reason": "Plain text content approximately 1800 chars (excluding code blocks). Subsections (プルダウン, ラジオボタン, チェックボックス) exist but lack explicit h3 underlines in source; treated as h3 content within single h2 section per expected sections list."
    },
    {
      "section_id": "checkbox-off-value",
      "source_heading": "チェックボックスでチェックなしに対する値を指定する",
      "heading_level": "h2",
      "h3_split": false,
      "h3_split_reason": "plain text content under 2000 chars; h3 subsection (実装例) consolidated within parent h2"
    },
    {
      "section_id": "window-scope",
      "source_heading": "入力データを画面間で持ち回る(ウィンドウスコープ)",
      "heading_level": "h2",
      "h3_split": false,
      "h3_split_reason": "Plain text content approximately 1800 chars < 2000 threshold. Expected Sections list contains only one entry; no h3 subsections split into separate sections."
    },
    {
      "section_id": "overview",
      "source_heading": "クライアントに保持するデータを暗号化する(hidden暗号化) - 概要",
      "heading_level": "h2-intro",
      "h3_split": true,
      "h3_split_reason": "plain text ~3000 chars > 2000 threshold with h3 subsections"
    },
    {
      "section_id": "hidden-encryption-mechanism",
      "source_heading": "hidden暗号化",
      "heading_level": "h3",
      "h3_split": true,
      "h3_split_reason": "h3 promoted to top-level section"
    },
    {
      "section_id": "encryption-process",
      "source_heading": "暗号化処理",
      "heading_level": "h3",
      "h3_split": true,
      "h3_split_reason": "h3 promoted to top-level section"
    },
    {
      "section_id": "decryption-process",
      "source_heading": "復号処理",
      "heading_level": "h3",
      "h3_split": true,
      "h3_split_reason": "h3 promoted to top-level section"
    },
    {
      "section_id": "key-storage",
      "source_heading": "暗号化に使用する鍵の保存場所",
      "heading_level": "h3",
      "h3_split": true,
      "h3_split_reason": "h3 promoted to top-level section"
    },
    {
      "section_id": "configuration",
      "source_heading": "hidden暗号化の設定",
      "heading_level": "h3",
      "h3_split": true,
      "h3_split_reason": "h3 promoted to top-level section"
    },
    {
      "section_id": "composite-key-radio-button-checkbox",
      "source_heading": "複合キーのラジオボタンやチェックボックスを作る",
      "heading_level": "h2",
      "h3_split": false,
      "h3_split_reason": "plain text 1200 chars < 2000 threshold; no h3 headings with underline markers (~~~~~) in source"
    },
    {
      "section_id": "multi-button-link-form-submit",
      "source_heading": "複数のボタン/リンクからフォームをサブミットする",
      "heading_level": "h2",
      "h3_split": false,
      "h3_split_reason": "plain text content approximately 800 characters, well under 2000 character threshold"
    },
    {
      "section_id": "submit-processing",
      "source_heading": "サブミット前に処理を追加する",
      "heading_level": "h2",
      "h3_split": false,
      "h3_split_reason": "plain text 680 chars < 2000 threshold; no h3 subsection headings with underlines found"
    },
    {
      "section_id": "dropdown-submit",
      "source_heading": "プルダウン変更などの画面操作でサブミットする",
      "heading_level": "h2",
      "h3_split": false,
      "h3_split_reason": "plain text ~700 chars < 2000 threshold, no h3 subsections"
    },
    {
      "section_id": "add-parameters-per-button-link",
      "source_heading": "ボタン/リンク毎にパラメータを追加する",
      "heading_level": "h2",
      "h3_split": false,
      "h3_split_reason": "plain text < 2000 chars, no h3 headings present"
    },
    {
      "section_id": "display-control-by-permission",
      "source_heading": "認可チェック/サービス提供可否に応じてボタン/リンクの表示/非表示を切り替える",
      "heading_level": "h2",
      "h3_split": false,
      "h3_split_reason": "Plain text under 2000 chars, no h3 headings with tilde underline found in source"
    },
    {
      "section_id": "popup-window-button-link",
      "source_heading": "別ウィンドウ/タブを開くボタン/リンクを作る(ポップアップ)",
      "heading_level": "h2",
      "h3_split": false,
      "h3_split_reason": "Expected sections provided with single h2 section; no h3 split applied despite h3 subsections in source"
    },
    {
      "section_id": "download-file-button-link",
      "source_heading": "ファイルをダウンロードするボタン/リンクを作る",
      "heading_level": "h2",
      "h3_split": false,
      "h3_split_reason": "No formal h3 headings with tilde underline exist; subsection titles (ダウンロードタグ, ダウンロードユーティリティ, etc.) are text content within the h2 section. Plain text content is over 2000 characters but h3 split rule does not apply without formal h3 heading underlines."
    },
    {
      "section_id": "preventing-double-submission",
      "source_heading": "二重サブミットを防ぐ",
      "heading_level": "h1",
      "h3_split": false,
      "h3_split_reason": "Expected Sections list contains only the main document heading. File is treated as a single knowledge section."
    },
    {
      "section_id": "server-token-database",
      "source_heading": "サーバ側のトークンをデータベースに保存する",
      "heading_level": "h2",
      "h3_split": false,
      "h3_split_reason": "plain text ~180 chars < 2000 threshold, no h3 headings"
    },
    {
      "section_id": "input-confirmation-shared",
      "source_heading": "入力画面と確認画面を共通化する",
      "heading_level": "h2"
    },
    {
      "section_id": "variable-setting",
      "source_heading": "変数に値を設定する",
      "heading_level": "h2",
      "h3_split": false,
      "h3_split_reason": "Plain text content is approximately 700-800 characters, well below 2000 character threshold. No h3-level subsections with explicit underlining detected."
    },
    {
      "section_id": "get-requests",
      "source_heading": "GETリクエストを使用する",
      "heading_level": "h2",
      "h3_split": false,
      "h3_split_reason": "Expected Sections specifies single section; no h3 headings with ~~~~~ underlines found in source"
    },
    {
      "section_id": "output-value",
      "source_heading": "値を出力する",
      "heading_level": "h2",
      "h3_split": false,
      "h3_split_reason": "plain text < 2000 chars; no h3 headings present"
    },
    {
      "section_id": "html-unescape-output",
      "source_heading": "HTMLエスケープせずに値を出力する",
      "heading_level": "h2",
      "h3_split": false,
      "h3_split_reason": "No h3 headings (~~~~~ underline) found in source. Content exceeds 2000 chars but uses :ref: labels for structure, not formal h3 headings. Per rule 2-2, kept as single section."
    },
    {
      "section_id": "format-values-output",
      "source_heading": "フォーマットして値を出力する",
      "heading_level": "h2",
      "h3_split": false,
      "h3_split_reason": "Plain text content exceeds 2000 characters, but no h3 headings with proper underline markup (~~~~) exist in source. Subsections (format, valueFormat属性, yyyymmdd, yyyymm, dateTime, decimal) are indicated by text labels and labels with .. _: directives, not proper h3 heading markup. Per rules, keeping as single section and including all subsection content consolidated."
    },
    {
      "section_id": "error-display",
      "source_heading": "エラー表示を行う",
      "heading_level": "h2",
      "h3_split": false,
      "h3_split_reason": "No formal h3 headings with explicit underlines; subsections marked with .. _label: are referenced sections, not split-level headings. Plain text ≈ 2000 chars, below strict split threshold."
    },
    {
      "section_id": "code-value-display",
      "source_heading": "コード値を表示する",
      "heading_level": "h2",
      "h3_split": false,
      "h3_split_reason": "Plain text content approximately 600 characters, which is less than the 2000-character threshold. No h3 headings with RST underlines detected in source."
    },
    {
      "section_id": "output-messages",
      "source_heading": "メッセージを出力する",
      "heading_level": "h2",
      "h3_split": false,
      "h3_split_reason": "plain text < 2000 chars; no formal h3 headings with underline found"
    },
    {
      "section_id": "language-based-resource-paths",
      "source_heading": "言語毎にリソースパスを切り替える",
      "heading_level": "h2",
      "h3_split": false,
      "h3_split_reason": "plain text < 2000 chars threshold (approximately 600 chars of content); no h3 headings in source"
    },
    {
      "section_id": "prevent-browser-cache",
      "source_heading": "ブラウザのキャッシュを防止する",
      "heading_level": "h2",
      "h3_split": false,
      "h3_split_reason": "plain text approximately 1050 characters < 2000 threshold; no h3 subsections present"
    },
    {
      "section_id": "static-content-cache-bypass",
      "source_heading": "静的コンテンツの変更時にクライアント側のキャッシュを参照しないようにする",
      "heading_level": "h2",
      "h3_split": false,
      "h3_split_reason": "plain text ~1000 chars < 2000 threshold; no h3 headings found in source"
    },
    {
      "section_id": "logical-attributes",
      "source_heading": "論理属性を指定する",
      "heading_level": "h2",
      "h3_split": false,
      "h3_split_reason": "plain text ~50 chars < 2000 threshold"
    },
    {
      "section_id": "arbitrary-attributes",
      "source_heading": "任意の属性を指定する",
      "heading_level": "h2",
      "h3_split": false,
      "h3_split_reason": "plain text 109 chars < 2000 threshold; no h3 subsections present"
    },
    {
      "section_id": "boolean-attributes",
      "source_heading": "論理属性の扱い",
      "heading_level": "h2",
      "h3_split": false,
      "h3_split_reason": "plain text ~415 chars < 2000 threshold, no h3 headings"
    },
    {
      "section_id": "csp-support",
      "source_heading": "Content Security Policy(CSP)に対応する",
      "heading_level": "h2",
      "h3_split": false,
      "h3_split_reason": "Plain text content approximately 310 characters < 2000 threshold. No h3 headings present in source."
    },
    {
      "section_id": "embed-nonce",
      "source_heading": "セキュアハンドラが生成したnonceを任意の要素に埋め込む",
      "heading_level": "h2",
      "h3_split": false,
      "h3_split_reason": "Plain text content is approximately 700 characters, below the 2000 character threshold for h3 splitting. No h3 headings found in source."
    },
    {
      "section_id": "javascript-processing",
      "source_heading": "カスタムタグが生成する要素に対してJavaScriptで処理を追加する",
      "heading_level": "h2",
      "h3_split": false,
      "h3_split_reason": "plain text approximately 500 chars < 2000 threshold; no h3 headings present"
    },
    {
      "section_id": "extension-examples",
      "source_heading": "拡張例",
      "heading_level": "h2",
      "h3_split": false,
      "h3_split_reason": "Plain text < 2000 chars; h3 subsections consolidated into single section"
    },
    {
      "section_id": "naming-rule",
      "source_heading": "命名ルール",
      "heading_level": "h2",
      "h3_split": false,
      "h3_split_reason": "No h3 subsections in source. Plain text content ~200 characters, well below 2000 character threshold"
    },
    {
      "section_id": "access-rule",
      "source_heading": "入力/出力データへのアクセスルール",
      "heading_level": "h2",
      "h3_split": false,
      "h3_split_reason": "No h3 subsections in source. Code examples excluded; plain text content ~1200 characters, below 2000 threshold"
    },
    {
      "section_id": "uri-specification",
      "source_heading": "URIの指定方法",
      "heading_level": "h2",
      "h3_split": false,
      "h3_split_reason": "No h3 subsections in source. Code examples excluded; plain text content ~1000 characters, below 2000 threshold"
    },
    {
      "section_id": "html-escape-and-conversion",
      "source_heading": "HTMLエスケープと改行、半角スペース変換",
      "heading_level": "h2",
      "h3_split": false,
      "h3_split_reason": "No h3 subsections in source. Plain text content ~300 characters, well below 2000 character threshold"
    },
    {
      "section_id": "tag-reference",
      "source_heading": ":ref:`tag_reference`",
      "heading_level": "h2",
      "h3_split": false,
      "h3_split_reason": "plain text < 2000 chars (approx 35 chars)"
    }
  ]
}