{
  "file_id": "adapters-doma_adaptor",
  "generated_at": "2026-03-07T07:39:45Z",
  "internal_labels": [],
  "sections": [
    {
      "section_id": "module-list",
      "source_heading": "モジュール一覧",
      "heading_level": "h2",
      "h3_split": false,
      "h3_split_reason": "plain text < 2000 chars; single code block and tip directive"
    },
    {
      "section_id": "setup",
      "source_heading": "Domaアダプタを使用するための設定を行う",
      "heading_level": "h2",
      "h3_split": false,
      "h3_split_reason": "Expected sections list specifies this as a single section; h3 subsections (依存関係の設定, ダイアレクトとデータソースの設定) included within parent"
    },
    {
      "section_id": "database-access",
      "source_heading": "Domaを使用してデータベースにアクセスする",
      "heading_level": "h2",
      "h3_split": false,
      "h3_split_reason": "Expected sections list specifies this as a single section; h3 subsections included within parent"
    },
    {
      "section_id": "separate-transaction",
      "source_heading": "別トランザクションで実行する",
      "heading_level": "h2",
      "h3_split": false,
      "h3_split_reason": "plain text < 2000 chars; no h3 headings"
    },
    {
      "section_id": "jakarta-batch",
      "source_heading": "Jakarta Batchに準拠したバッチアプリケーションで使用する",
      "heading_level": "h2",
      "h3_split": false,
      "h3_split_reason": "Expected sections list specifies this as a single section"
    },
    {
      "section_id": "jakarta-batch-lazy-load",
      "source_heading": "Jakarta Batchに準拠したバッチアプリケーションで遅延ロードを行う",
      "heading_level": "h2",
      "h3_split": false,
      "h3_split_reason": "Expected sections list specifies this as a single section"
    },
    {
      "section_id": "multiple-databases",
      "source_heading": "複数のデータベースにアクセスする",
      "heading_level": "h2",
      "h3_split": false,
      "h3_split_reason": "Expected sections list specifies this as a single section; h3 subsections included within parent"
    },
    {
      "section_id": "doma-nablarch-combined",
      "source_heading": "DomaとNablarchのデータベースアクセスを併用する",
      "heading_level": "h2",
      "h3_split": false,
      "h3_split_reason": "plain text < 2000 chars; no h3 headings"
    },
    {
      "section_id": "logger-switch",
      "source_heading": "ロガーを切り替える",
      "heading_level": "h2",
      "h3_split": false,
      "h3_split_reason": "plain text < 2000 chars; no h3 headings"
    },
    {
      "section_id": "java-sql-statement-settings",
      "source_heading": "java.sql.Statementに関する設定を行う",
      "heading_level": "h2",
      "h3_split": false,
      "h3_split_reason": "plain text ~300 chars < 2000 threshold; no h3 headings present"
    },
    {
      "section_id": "migration-from-doma-2-44-0",
      "source_heading": "Doma 2.44.0までの実装方法から移行する",
      "heading_level": "h2",
      "h3_split": false,
      "h3_split_reason": "plain text ~870 chars < 2000 threshold; h3 headings present but below threshold so kept as one section"
    }
  ]
}