{
  "file_id": "nablarch-patterns-Nablarchでの非同期処理",
  "generated_at": "2026-03-07T11:14:58Z",
  "sections": [
    {
      "section_id": "overview",
      "source_heading": "Nablarchでの非同期処理",
      "heading_level": "h1",
      "h3_split": false,
      "h3_split_reason": "plain text < 2000 chars, no h3 headings; intro content under h1 before first h2"
    },
    {
      "section_id": "mail-sending",
      "source_heading": "メール送信を行う場合",
      "heading_level": "h2",
      "h3_split": false,
      "h3_split_reason": "plain text < 2000 chars, no h3 headings"
    }
  ]
}