{
  "file_id": "blank-project-setup_NablarchBatch_Dbless--s1",
  "status": "has_issues",
  "findings": [
    {
      "category": "omission",
      "severity": "minor",
      "location": "s3 (ブランクプロジェクト作成)",
      "description": "mvnコマンドを実行する前に、ブランクプロジェクトを作成したいディレクトリにカレントディレクトリを変更するという前提手順が省略されている。",
      "source_evidence": "カレントディレクトリを、ブランクプロジェクトを作成したいディレクトリ(任意のディレクトリで可)に変更する。その後、以下のコマンドを実行する。"
    },
    {
      "category": "omission",
      "severity": "minor",
      "location": "s3 (ブランクプロジェクト作成)",
      "description": "プロジェクト情報の入力後に表示される「Y: :」の確認プロンプトと、Y（生成）またはN（やり直し）を入力する手順が省略されている。",
      "source_evidence": "プロジェクト情報の入力が終わると、Y: :と表示される。入力した内容をもとに、ひな形を生成する場合には「Y」を入力してください。プロジェクト情報の入力をやり直したい場合には「N」を入力してください。"
    },
    {
      "category": "omission",
      "severity": "minor",
      "location": "s3 (ブランクプロジェクト作成)",
      "description": "コマンド正常終了後にブランクプロジェクトがカレントディレクトリ配下に作成されるという結果の説明が省略されている。",
      "source_evidence": "コマンドが正常終了した場合、ブランクプロジェクトがカレントディレクトリ配下に作成される。"
    },
    {
      "category": "omission",
      "severity": "minor",
      "location": "s4 (疎通確認)",
      "description": "mvn test 実行成功時のコンソール出力例（「Tests run: 1, Failures: 0, Errors: 0, Skipped: 0」および「BUILD SUCCESS」を含むログ）が省略されている。ユーザーがセットアップ成功を確認する際に必要な情報。",
      "source_evidence": "[INFO] Tests run: 1, Failures: 0, Errors: 0, Skipped: 0 / [INFO] BUILD SUCCESS (実行成功時のログ出力例)"
    },
    {
      "category": "omission",
      "severity": "minor",
      "location": "s4 (疎通確認)",
      "description": "都度起動バッチアプリケーション起動成功時のコンソール出力例（「疎通確認を開始します」「疎通確認が完了しました」「exit code = [0]」等を含むログ）が省略されている。ユーザーが起動成功を確認する際に必要な情報。",
      "source_evidence": "2020-04-28 08:56:23.353 -INFO- com.example.SampleBatch [...] 疎通確認を開始します。 / @@@@ END @@@@ exit code = [0] execute time(ms) = [559] (起動成功時のログ出力例)"
    }
  ]
}