{
  "file_id": "libraries-02_02_Repository_initialize",
  "status": "has_issues",
  "findings": [
    {
      "category": "omission",
      "severity": "minor",
      "location": "s1 — コンポーネント設定ファイルの定義 (XML code block comment)",
      "description": "The XML comment explaining that components listed in initializeList (message, code) must be defined separately using <component> elements, and that <component-ref> is only for referencing already-defined components, is not captured in the knowledge file. This context clarifies the required structure of the component configuration file.",
      "source_evidence": "<!-- 初期化が必要なコンポーネント。message 、 code は別途 component 要素で定義されており、ここでは他で定義したコンポーネントヘの参照のみを記述する。 -->"
    }
  ]
}