{
  "file_id": "ui-framework-field_pulldown",
  "status": "has_issues",
  "findings": [
    {
      "category": "omission",
      "severity": "minor",
      "location": "s2 — nameAlias row in attribute table",
      "description": "The source description for `nameAlias` is \"一つのエラーメッセージに対して複数の入力項目をハイライト表示する場合に指定する\" but the knowledge file condenses it to \"複数入力項目をハイライト表示する場合に指定\", omitting \"一つのエラーメッセージに対して\". This phrase clarifies the precise use case: one error message highlighting multiple fields, which is decision-relevant context for developers choosing whether to use this attribute.",
      "source_evidence": "nameAlias | 一つのエラーメッセージに対して複数の入力項目をハイライト表示する場合に指定する。 | 文字列 | ○ | × |"
    }
  ]
}