{
  "id": "libraries-04_Permission--s10",
  "title": "使用方法",
  "no_knowledge_content": false,
  "official_doc_urls": [],
  "index": [
    {
      "id": "s1",
      "title": "使用方法",
      "hints": [
        "PermissionCheckHandler",
        "BasicPermissionFactory",
        "nablarch.common.handler.PermissionCheckHandler",
        "nablarch.common.permission.BasicPermissionFactory",
        "GroupTableSchema",
        "SystemAccountTableSchema",
        "GroupSystemAccountTableSchema",
        "PermissionUnitTableSchema",
        "PermissionUnitRequestTableSchema",
        "GroupAuthorityTableSchema",
        "SystemAccountAuthorityTableSchema",
        "nablarch.common.permission.schema.GroupTableSchema",
        "nablarch.common.permission.schema.SystemAccountTableSchema",
        "nablarch.common.permission.schema.GroupSystemAccountTableSchema",
        "nablarch.common.permission.schema.PermissionUnitTableSchema",
        "nablarch.common.permission.schema.PermissionUnitRequestTableSchema",
        "nablarch.common.permission.schema.GroupAuthorityTableSchema",
        "nablarch.common.permission.schema.SystemAccountAuthorityTableSchema",
        "BasicApplicationInitializer",
        "PermissionUtil",
        "SimpleDbTransactionManager",
        "permissionFactory",
        "ignoreRequestIds",
        "dbManager",
        "groupTableSchema",
        "systemAccountTableSchema",
        "groupSystemAccountTableSchema",
        "permissionUnitTableSchema",
        "permissionUnitRequestTableSchema",
        "groupAuthorityTableSchema",
        "systemAccountAuthorityTableSchema",
        "businessDateProvider",
        "tableName",
        "groupIdColumnName",
        "userIdColumnName",
        "userIdLockedColumnName",
        "failedCountColumnName",
        "effectiveDateFromColumnName",
        "effectiveDateToColumnName",
        "permissionUnitIdColumnName",
        "requestIdColumnName",
        "認可判定",
        "権限チェック",
        "認可設定",
        "DIコンテナ認可設定",
        "ignoreRequestIds除外設定",
        "BasicBusinessDateProvider",
        "BusinessDateProvider",
        "Permission"
      ]
    }
  ],
  "sections": {
    "s1": "## BasicPermissionFactoryの設定方法\n\n**クラス**: `nablarch.common.handler.PermissionCheckHandler`, `nablarch.common.permission.BasicPermissionFactory`\n\nPermissionCheckHandlerとBasicPermissionFactoryをDIコンテナで設定する。設定例:\n\n```xml\n<component name=\"webFrontController\"\n           class=\"nablarch.fw.web.servlet.WebFrontController\">\n    <property name=\"handlerQueue\">\n        <list>\n            <component class=\"nablarch.fw.RequestHandlerEntry\">\n                <property name=\"requestPattern\" value=\"/action//\" />\n                <property name=\"handler\">\n                    <component class=\"nablarch.common.handler.PermissionCheckHandler\">\n                        <property name=\"permissionFactory\" ref=\"permissionFactory\" />\n                        <property name=\"ignoreRequestIds\" value=\"RW11AA0101, RW11AA0102, RW99ZZ0601, RW99ZZ0602, RW99ZZ0603, RW99ZZ0604, RW99ZZ0605\" />\n                    </component>\n                </property>\n            </component>\n        </list>\n    </property>\n</component>\n\n<component name=\"permissionFactory\" class=\"nablarch.common.permission.BasicPermissionFactory\">\n    <property name=\"dbManager\">\n        <component class=\"nablarch.core.db.transaction.SimpleDbTransactionManager\">\n            <property name=\"dbTransactionName\" value=\"PermissionCheck\" />\n            <property name=\"transactionFactory\" ref=\"transactionFactory\" />\n            <property name=\"connectionFactory\" ref=\"connectionFactory\" />\n        </component>\n    </property>\n    <property name=\"groupTableSchema\">\n        <component class=\"nablarch.common.permission.schema.GroupTableSchema\">\n            <property name=\"tableName\" value=\"UGROUP\" />\n            <property name=\"groupIdColumnName\" value=\"UGROUP_ID\" />\n        </component>\n    </property>\n    <property name=\"systemAccountTableSchema\">\n        <component class=\"nablarch.common.permission.schema.SystemAccountTableSchema\">\n            <property name=\"tableName\" value=\"SYSTEM_ACCOUNT\" />\n            <property name=\"userIdColumnName\" value=\"USER_ID\" />\n            <property name=\"userIdLockedColumnName\" value=\"USER_ID_LOCKED\" />\n            <property name=\"effectiveDateFromColumnName\" value=\"EFFECTIVE_DATE_FROM\" />\n            <property name=\"effectiveDateToColumnName\" value=\"EFFECTIVE_DATE_TO\" />\n        </component>\n    </property>\n    <property name=\"groupSystemAccountTableSchema\">\n        <component class=\"nablarch.common.permission.schema.GroupSystemAccountTableSchema\">\n            <property name=\"tableName\" value=\"UGROUP_SYSTEM_ACCOUNT\" />\n            <property name=\"groupIdColumnName\" value=\"UGROUP_ID\" />\n            <property name=\"userIdColumnName\" value=\"USER_ID\" />\n            <property name=\"effectiveDateFromColumnName\" value=\"EFFECTIVE_DATE_FROM\" />\n            <property name=\"effectiveDateToColumnName\" value=\"EFFECTIVE_DATE_TO\" />\n        </component>\n    </property>\n    <property name=\"permissionUnitTableSchema\">\n        <component class=\"nablarch.common.permission.schema.PermissionUnitTableSchema\">\n            <property name=\"tableName\" value=\"PERMISSION_UNIT\" />\n            <property name=\"permissionUnitIdColumnName\" value=\"PERMISSION_UNIT_ID\" />\n        </component>\n    </property>\n    <property name=\"permissionUnitRequestTableSchema\">\n        <component class=\"nablarch.common.permission.schema.PermissionUnitRequestTableSchema\">\n            <property name=\"tableName\" value=\"PERMISSION_UNIT_REQUEST\" />\n            <property name=\"permissionUnitIdColumnName\" value=\"PERMISSION_UNIT_ID\" />\n            <property name=\"requestIdColumnName\" value=\"REQUEST_ID\" />\n        </component>\n    </property>\n    <property name=\"groupAuthorityTableSchema\">\n        <component class=\"nablarch.common.permission.schema.GroupAuthorityTableSchema\">\n            <property name=\"tableName\" value=\"UGROUP_AUTHORITY\" />\n            <property name=\"groupIdColumnName\" value=\"UGROUP_ID\" />\n            <property name=\"permissionUnitIdColumnName\" value=\"PERMISSION_UNIT_ID\" />\n        </component>\n    </property>\n    <property name=\"systemAccountAuthorityTableSchema\">\n        <component class=\"nablarch.common.permission.schema.SystemAccountAuthorityTableSchema\">\n            <property name=\"tableName\" value=\"SYSTEM_ACCOUNT_AUTHORITY\" />\n            <property name=\"userIdColumnName\" value=\"USER_ID\" />\n            <property name=\"permissionUnitIdColumnName\" value=\"PERMISSION_UNIT_ID\" />\n        </component>\n    </property>\n    <property name=\"businessDateProvider\" ref=\"businessDateProvider\" />\n</component>\n\n<component name=\"businessDateProvider\" class=\"nablarch.core.date.BasicBusinessDateProvider\" />\n```\n\nスキーマ情報クラス一覧:\n\n| クラス名 | 概要 |\n|---|---|\n| `nablarch.common.permission.schema.GroupTableSchema` | グループテーブルのスキーマ情報 |\n| `nablarch.common.permission.schema.SystemAccountTableSchema` | システムアカウントテーブルのスキーマ情報 |\n| `nablarch.common.permission.schema.GroupSystemAccountTableSchema` | グループシステムアカウントテーブルのスキーマ情報 |\n| `nablarch.common.permission.schema.PermissionUnitTableSchema` | 認可単位テーブルのスキーマ情報 |\n| `nablarch.common.permission.schema.PermissionUnitRequestTableSchema` | 認可単位リクエストテーブルのスキーマ情報 |\n| `nablarch.common.permission.schema.GroupAuthorityTableSchema` | グループ権限テーブルのスキーマ情報 |\n| `nablarch.common.permission.schema.SystemAccountAuthorityTableSchema` | システムアカウント権限テーブルのスキーマ情報 |\n\n### PermissionCheckHandlerの設定\n\n| プロパティ名 | 必須 | 説明 |\n|---|---|---|\n| permissionFactory | ○ | Permissionを生成するPermissionFactory |\n| ignoreRequestIds | | 認可判定を行わないリクエストID（複数指定はカンマ区切り） |\n\n### BasicPermissionFactoryの設定\n\n| プロパティ名 | 必須 | 説明 |\n|---|---|---|\n| dbManager | ○ | SimpleDbTransactionManagerのインスタンス（:doc:`../01_Core/04_DbAccessSpec` 参照） |\n| groupTableSchema | ○ | GroupTableSchemaクラスのインスタンス |\n| systemAccountTableSchema | ○ | SystemAccountTableSchemaクラスのインスタンス |\n| groupSystemAccountTableSchema | ○ | GroupSystemAccountTableSchemaクラスのインスタンス |\n| permissionUnitTableSchema | ○ | PermissionUnitTableSchemaクラスのインスタンス |\n| permissionUnitRequestTableSchema | ○ | PermissionUnitRequestTableSchemaクラスのインスタンス |\n| groupAuthorityTableSchema | ○ | GroupAuthorityTableSchemaクラスのインスタンス |\n| systemAccountAuthorityTableSchema | ○ | SystemAccountAuthorityTableSchemaクラスのインスタンス |\n| businessDateProvider | ○ | BusinessDateProviderのインスタンス。有効日（From/To）のチェックに使用（:ref:`BusinessDateProvider-label` 参照） |\n\n### GroupTableSchemaの設定\n\n| プロパティ名 | 必須 | 説明 |\n|---|---|---|\n| tableName | ○ | テーブル名 |\n| groupIdColumnName | ○ | グループIDカラムの名前 |\n\n### SystemAccountTableSchemaの設定\n\n| プロパティ名 | 必須 | 説明 |\n|---|---|---|\n| tableName | ○ | テーブル名 |\n| userIdColumnName | ○ | ユーザIDカラムの名前 |\n| userIdLockedColumnName | ○ | ユーザIDロックカラムの名前 |\n| failedCountColumnName | ○ | 認証失敗回数カラムの名前 |\n| effectiveDateFromColumnName | ○ | 有効日(From)カラムの名前 |\n| effectiveDateToColumnName | ○ | 有効日(To)カラムの名前 |\n\n### GroupSystemAccountTableSchemaの設定\n\n| プロパティ名 | 必須 | 説明 |\n|---|---|---|\n| tableName | ○ | テーブル名 |\n| groupIdColumnName | ○ | グループIDカラムの名前 |\n| userIdColumnName | ○ | ユーザIDカラムの名前 |\n| effectiveDateFromColumnName | ○ | 有効日(From)カラムの名前 |\n| effectiveDateToColumnName | ○ | 有効日(To)カラムの名前 |\n\n### PermissionUnitTableSchemaの設定\n\n| プロパティ名 | 必須 | 説明 |\n|---|---|---|\n| tableName | ○ | テーブル名 |\n| permissionUnitIdColumnName | ○ | 認可単位IDカラムの名前 |\n\n### PermissionUnitRequestTableSchemaの設定\n\n| プロパティ名 | 必須 | 説明 |\n|---|---|---|\n| tableName | ○ | テーブル名 |\n| permissionUnitIdColumnName | ○ | 認可単位IDカラムの名前 |\n| requestIdColumnName | ○ | リクエストIDカラムの名前 |\n\n### GroupAuthorityTableSchemaの設定\n\n| プロパティ名 | 必須 | 説明 |\n|---|---|---|\n| tableName | ○ | テーブル名 |\n| groupIdColumnName | ○ | グループIDカラムの名前 |\n| permissionUnitIdColumnName | ○ | 認可単位IDカラムの名前 |\n\n### SystemAccountAuthorityTableSchemaの設定\n\n| プロパティ名 | 必須 | 説明 |\n|---|---|---|\n| tableName | ○ | テーブル名 |\n| userIdColumnName | ○ | ユーザIDカラムの名前 |\n| permissionUnitIdColumnName | ○ | 認可単位IDカラムの名前 |\n\nBasicPermissionFactoryは :ref:`repository_initialize` のInitializableインタフェースを実装しているため、BasicApplicationInitializerで初期化設定が必要:\n\n```xml\n<component name=\"initializer\" class=\"nablarch.core.repository.initialization.BasicApplicationInitializer\">\n    <property name=\"initializeList\">\n        <list>\n            <component-ref name=\"permissionFactory\"/>\n        </list>\n    </property>\n</component>\n```\n\n## 特定のリクエストIDを認可判定の対象から除外する方法\n\nログイン処理など一部の処理を認可判定から除外するには、PermissionCheckHandlerの`ignoreRequestIds`プロパティにリクエストIDをカンマ区切りで指定する。\n\n```xml\n<component class=\"nablarch.common.handler.PermissionCheckHandler\">\n    <property name=\"permissionFactory\" ref=\"permissionFactory\" />\n    <property name=\"ignoreRequestIds\" value=\"RW11AA0101, RW11AA0102\" />\n</component>\n```\n\n## 認可判定の使用例\n\n> **注意**: 下記のコードはフレームワークが行う処理であり、通常のアプリケーションでは実装する必要がない。\n\n```java\n// PermissionCheckHandlerにより、スレッドローカルにPermissionが保持されている。\nPermission permission = PermissionUtil.getPermission();\n\nif (permission.permit(\"リクエストID\")) {\n    // 認可に成功した場合の処理\n} else {\n    // 認可に失敗した場合の処理\n}\n```"
  }
}