{
  "file_id": "web-application-inputAndOutput--s8",
  "status": "has_issues",
  "findings": [
    {
      "category": "fabrication",
      "severity": "minor",
      "location": "s3",
      "description": "The knowledge file assigns specific roles to errorsタグ (\"エラーメッセージの一覧表示\") and errorタグ (\"個別エラーメッセージの表示\"), but the source only lists the two tags without describing a distinction between them.",
      "source_evidence": "Source: 「単項目精査エラーや業務エラーなどが発生したときの、エラーメッセージ表示のために以下のタグを提供する。 * errorsタグ * errorタグ」— no descriptions of what each tag does individually."
    }
  ]
}