{
  "file_id": "about-nablarch-versionup_policy--s1",
  "status": "has_issues",
  "findings": [
    {
      "category": "fabrication",
      "severity": "minor",
      "location": "s3",
      "description": "The knowledge file adds \"（標準/ガイド、ライブラリ、ツール等）\" as examples of non-framework contents, but the source sentence in this section simply states \"Nablarchフレームワーク以外のコンテンツに対する後方互換性の維持は考慮されません\" without any such parenthetical examples.",
      "source_evidence": "Source: 「なお、Nablarchフレームワーク以外のコンテンツに対する後方互換性の維持は考慮されません。」— no examples listed"
    },
    {
      "category": "omission",
      "severity": "minor",
      "location": "s4",
      "description": "The \"出来る限り\" (best-effort / as much as possible) qualifier in the backward compatibility goals is dropped. The source says \"出来る限り下記を発生させないよう考慮します\" (will try as much as possible not to cause …), but the knowledge file renders this as simply \"下記を発生させないよう考慮する:\", removing the best-effort nuance and making the commitment sound more absolute than the source intends.",
      "source_evidence": "Source: 「Nablarchフレームワークのバージョンアップを行った場合に、出来る限り下記を発生させないよう考慮します。」"
    }
  ]
}