{
  "file_id": "libraries-02_SqlLog--s17",
  "status": "has_issues",
  "findings": [
    {
      "category": "omission",
      "severity": "critical",
      "location": "SQLログの出力例 section (source heading with ===)",
      "description": "The entire 'SQLログの出力例' section content is missing from the knowledge file. This section contains: (1) a log.properties configuration example showing how to configure FileLogWriter, BasicLogFormatter, availableLoggersNamesOrder, and the SQL logger with TRACE level; (2) an app-log.properties configuration example showing sqlLogFormatter.startRetrieveFormat and sqlLogFormatter.endRetrieveFormat settings; and (3) actual log output showing real log entries from a retrieve operation. This is concrete configuration guidance essential for users trying to set up SQL logging.",
      "source_evidence": "Source section 'SQLログの出力例' contains log.properties with writerNames, writer.appFile.className, writer.appFile.filePath, writer.appFile.encoding, writer.appFile.maxFileSize, writer.appFile.formatter settings, availableLoggersNamesOrder=SQL, loggers.SQL.nameRegex/level/writerNames; app-log.properties with sqlLogFormatter.startRetrieveFormat and sqlLogFormatter.endRetrieveFormat; and a full actual log output block showing timestamped SQL log entries."
    }
  ]
}