{
  "file_id": "ui-framework-spec_layout",
  "status": "has_issues",
  "findings": [
    {
      "category": "omission",
      "severity": "critical",
      "location": "内部構造・改修時の留意点 section",
      "description": "The entire '内部構造・改修時の留意点' section is omitted. This section contains substantive technical information: (1) layout.tag is a nearly empty dummy for JSP compilation containing only `<jsp:doBody>`; (2) the design document view is composed of SpecSheetTemplate.xlsx (template file) and SpecSheetInterpreter.js (display content control script). This context is relevant for developers troubleshooting server-side rendering or modifying the widget.",
      "source_evidence": "サーバ表示で動作するタグファイル(layout.tag) は、JSPコンパイルを通すためだけの、ほぼ中身のないダミーである。(<jsp:doBody> のみを記述)\n設計書ビューはテンプレートファイルである SpecSheetTemplate.xlsx と、各項目の表示内容を制御する SpecSheetInterpreter.js によって構成される。"
    }
  ]
}