{
  "file_id": "ui-framework-event_window_close",
  "status": "has_issues",
  "findings": [
    {
      "category": "omission",
      "severity": "minor",
      "location": "s2 (仕様 — 属性値一覧)",
      "description": "The `内容` column is missing from the attribute table. The source table has six columns: 名称, 内容, タイプ, サーバ, ローカル, 備考. The knowledge file renders only five columns (名称, タイプ, サーバ, ローカル, 備考), dropping the `内容` value `処理内容の簡単な説明` for the `title` attribute.",
      "source_evidence": "title | 処理内容の簡単な説明 | 文字列 | × | × | 設計書表示用"
    }
  ]
}