{
  "id": "about-nablarch-terms_of_use",
  "title": "ご利用にあたって",
  "official_doc_urls": [
    "https://nablarch.github.io/docs/LATEST/doc/terms_of_use/index.html",
    "https://plausible.io",
    "https://plausible.io/data-policy"
  ],
  "processing_patterns": [],
  "index": [
    {
      "id": "usage-purpose",
      "title": "情報の利用目的",
      "hints": [
        "アクセス解析",
        "情報収集",
        "匿名収集",
        "サイト改善"
      ]
    },
    {
      "id": "transmission-destination",
      "title": "情報の送信先",
      "hints": [
        "Plausible Analytics",
        "アクセス情報送信先",
        "外部送信"
      ]
    },
    {
      "id": "data-types-and-usage",
      "title": "情報の種類・用途",
      "hints": [
        "ページのURL",
        "リファラー",
        "ブラウザ",
        "OS",
        "デバイス種別",
        "位置情報",
        "ユーザーエージェント",
        "IPアドレス"
      ]
    }
  ],
  "sections": {
    "usage-purpose": "取得した情報はアクセス解析に利用される。ページのアクセス数等からサイトの利用状況を把握し、サイトの改善に利用する。アクセス情報は匿名で収集され、個人を特定することはできない。",
    "transmission-destination": "取得した情報は [Plausible Analytics](https://plausible.io) に送信される。",
    "data-types-and-usage": "| 情報の種類 | 例 | 説明 | 用途 |\n|---|---|---|---|\n| ページのURL | [https://nablarch.github.io/docs/LATEST/doc/index.html](https://nablarch.github.io/docs/LATEST/doc/index.html) | 当ウェブサイトのURL | どのページが閲覧されたか測定 |\n| リファラー | https://x.com/ | 参照元ページ | どのページから当サイトに到達したかを測定 |\n| ブラウザ | Chrome 86.0 | 利用者のブラウザの種類 | 利用者の閲覧環境を測定[1] |\n| OS | macOS 10.15 | 利用者のOSの種類 | 利用者の閲覧環境を測定[2] |\n| デバイス種別 | Desktop | 利用者のデバイスの種類 | 利用者の閲覧環境を測定[3] |\n| 国、地域、都市 | United Kingdom, England, London | 利用者の位置情報 | 利用者の閲覧環境を測定[4] |\n\n[1] ユーザーエージェントから取得するが、必要な情報だけを使用する。完全なユーザーエージェントは破棄される。\n[2] ユーザーエージェントから取得するが、必要な情報だけを使用する。完全なユーザーエージェントは破棄される。\n[3] ユーザーエージェントから取得するが、必要な情報だけを使用する。完全なユーザーエージェントは破棄される。\n[4] IPアドレスを使用して位置情報を取得するが、都市レベルより詳細な追跡は行わない。IPアドレスは破棄されるため、データベース等に保存されることはない。\n\n詳細は [Plausible Analyticsのポリシー](https://plausible.io/data-policy) を参照。"
  }
}